odoo10_addon_hr_timesheet_sheet_week_start_day-10.0.1.0.0-py2.7-nspkg.pth
odoo/addons/hr_timesheet_sheet_week_start_day/README.rst
odoo/addons/hr_timesheet_sheet_week_start_day/__init__.py
odoo/addons/hr_timesheet_sheet_week_start_day/__manifest__.py
odoo/addons/hr_timesheet_sheet_week_start_day/models/__init__.py
odoo/addons/hr_timesheet_sheet_week_start_day/models/hr_timesheet_sheet.py
odoo/addons/hr_timesheet_sheet_week_start_day/models/project_config_settings.py
odoo/addons/hr_timesheet_sheet_week_start_day/models/res_company.py
odoo/addons/hr_timesheet_sheet_week_start_day/static/description/icon.png
odoo/addons/hr_timesheet_sheet_week_start_day/tests/__init__.py
odoo/addons/hr_timesheet_sheet_week_start_day/tests/test_hr_timesheet_sheet_week_start_day.py
odoo/addons/hr_timesheet_sheet_week_start_day/views/project_config_settings_view.xml
odoo10_addon_hr_timesheet_sheet_week_start_day-10.0.1.0.0.dist-info/DESCRIPTION.rst
odoo10_addon_hr_timesheet_sheet_week_start_day-10.0.1.0.0.dist-info/METADATA
odoo10_addon_hr_timesheet_sheet_week_start_day-10.0.1.0.0.dist-info/RECORD
odoo10_addon_hr_timesheet_sheet_week_start_day-10.0.1.0.0.dist-info/WHEEL
odoo10_addon_hr_timesheet_sheet_week_start_day-10.0.1.0.0.dist-info/metadata.json
odoo10_addon_hr_timesheet_sheet_week_start_day-10.0.1.0.0.dist-info/namespace_packages.txt
odoo10_addon_hr_timesheet_sheet_week_start_day-10.0.1.0.0.dist-info/top_level.txt
