Metadata-Version: 2.0
Name: odoo10-addon-hr-timesheet-sheet-week-start-day
Version: 10.0.1.0.0
Summary: Allows to define the week start date for Timesheets at company level
Home-page: http://www.eficent.com
Author: Eficent Business and IT Consulting Services, S.L., Odoo Community Association (OCA)
Author-email: support@odoo-community.org
License: AGPL-3
Platform: UNKNOWN
Classifier: Programming Language :: Python :: 2.7
Classifier: Framework :: Odoo
Classifier: License :: OSI Approved :: GNU Affero General Public License v3
Requires-Dist: odoo (<10.1dev,>=10.0)
